beamer_gen/__init__.py
beamer_gen/beamer_gen.py
beamer_gen-1.6.0.dist-info/LICENSE
beamer_gen-1.6.0.dist-info/METADATA
beamer_gen-1.6.0.dist-info/WHEEL
beamer_gen-1.6.0.dist-info/entry_points.txt
beamer_gen-1.6.0.dist-info/top_level.txt
beamer_gen-1.6.0.dist-info/RECORD
